lbpytest/__init__.py
lbpytest/conftest.py
lbpytest/controlmaster.py
lbpytest/incremental_line_split.py
lbpytest/logscan.py
lbpytest/test_controlmaster.py
lbpytest/test_incremental_line_split.py
lbpytest/test_logscan.py
lbpytest/test_logscan_ssh.py
lbpytest-0.4.0.dist-info/LICENSE
lbpytest-0.4.0.dist-info/METADATA
lbpytest-0.4.0.dist-info/WHEEL
lbpytest-0.4.0.dist-info/top_level.txt
lbpytest-0.4.0.dist-info/RECORD
