Metadata-Version: 2.2
Name: lbpytest
Version: 0.4.0
Summary: Utilities for Python-driven integration tests at LINBIT
Home-page: https://github.com/LINBIT/lbpytest
Author: Christoph Böhmwalder
Author-email: christoph.boehmwalder@linbit.com
Project-URL: Bug Tracker, https://github.com/LINBIT/lbpytest/issues
Classifier: Programming Language :: Python :: 3
Classifier: License :: OSI Approved :: MIT License
Classifier: Operating System :: POSIX :: Linux
Requires-Python: >=3.10
License-File: LICENSE
